image_utils/__init__.py
image_utils/image_utils.py
whops_image_utils-0.1.0.dist-info/licenses/LICENSE
whops_image_utils-0.1.0.dist-info/METADATA
whops_image_utils-0.1.0.dist-info/WHEEL
whops_image_utils-0.1.0.dist-info/top_level.txt
whops_image_utils-0.1.0.dist-info/RECORD
